<annotation>
  <folder>JPEGImages</folder>
  <filename>B0048_0031.png</filename>
  <path>JPEGImages\B0048_0031.png</path>
  <source>
    <database>GDXRay</database>
  </source>
  <size>
    <width>2688</width>
    <height>2208</height>
    <depth>1</depth>
  </size>
  <object>
    <name>Handgun</name>
    <pose>Unspecified</pose>
    <truncated>0</truncated>
    <difficult>0</difficult>
    <bndbox>
      <xmin>1213</xmin>
      <ymin>892</ymin>
      <xmax>1886</xmax>
      <ymax>1649</ymax>
    </bndbox>
  </object>
  <object>
    <name>RazorBlade</name>
    <pose>Unspecified</pose>
    <truncated>0</truncated>
    <difficult>0</difficult>
    <bndbox>
      <xmin>1140</xmin>
      <ymin>1091</ymin>
      <xmax>1437</xmax>
      <ymax>1372</ymax>
    </bndbox>
  </object>
</annotation>
