<annotation>
  <folder>JPEGImages</folder>
  <filename>B0048_0193.png</filename>
  <path>JPEGImages\B0048_0193.png</path>
  <source>
    <database>GDXRay</database>
  </source>
  <size>
    <width>2688</width>
    <height>2208</height>
    <depth>1</depth>
  </size>
  <object>
    <name>Shuriken</name>
    <pose>Unspecified</pose>
    <truncated>0</truncated>
    <difficult>0</difficult>
    <bndbox>
      <xmin>1184</xmin>
      <ymin>191</ymin>
      <xmax>1842</xmax>
      <ymax>943</ymax>
    </bndbox>
  </object>
  <object>
    <name>Handgun</name>
    <pose>Unspecified</pose>
    <truncated>0</truncated>
    <difficult>0</difficult>
    <bndbox>
      <xmin>1061</xmin>
      <ymin>960</ymin>
      <xmax>1757</xmax>
      <ymax>2124</ymax>
    </bndbox>
  </object>
</annotation>
